batchmatch/__init__.py
batchmatch/filters.py
batchmatch/library.py
batchmatch/smarts.py
batchmatch-0.1.0.dist-info/licenses/LICENSE
batchmatch-0.1.0.dist-info/METADATA
batchmatch-0.1.0.dist-info/WHEEL
batchmatch-0.1.0.dist-info/top_level.txt
batchmatch-0.1.0.dist-info/RECORD
