Metadata-Version: 2.4
Name: batchmatch
Version: 0.1.0
Summary: Fast matching to a batch of molecular patterns.
Author-email: Alston Lo <alston@mit.edu>
License: MIT
Project-URL: repository, https://github.com/alstonlo/batchmatch
Requires-Python: >=3.8
License-File: LICENSE
Requires-Dist: numpy
Requires-Dist: networkx
Requires-Dist: rdkit
Provides-Extra: dev
Requires-Dist: pytest; extra == "dev"
Requires-Dist: tqdm; extra == "dev"
Requires-Dist: polars; extra == "dev"
Dynamic: license-file
